do_problem_solving-0.1.0.dist-info/METADATA
do_problem_solving-0.1.0.dist-info/WHEEL
do_problem_solving-0.1.0.dist-info/entry_points.txt
do_problem_solving-0.1.0.dist-info/licenses/LICENSE
do_problem_solving/__init__.py
do_problem_solving/__main__.py
do_problem_solving-0.1.0.dist-info/RECORD
